ipf_tables_to_excel/main.py
ipfabric_tables_to_excel-0.1.1.dist-info/METADATA
ipfabric_tables_to_excel-0.1.1.dist-info/WHEEL
ipfabric_tables_to_excel-0.1.1.dist-info/entry_points.txt
ipfabric_tables_to_excel-0.1.1.dist-info/RECORD
