Metadata-Version: 2.1
Name: ipfabric-tables-to-excel
Version: 0.1.1
Summary: Command Line tool to export IP Fabric Tables to Excel
License: MIT
Author: Cristian Cordero
Author-email: cristian.cordero@ipfabric.io
Requires-Python: >=3.9,<4.0
Classifier: License :: OSI Approved :: MIT License
Classifier: Programming Language :: Python :: 3
Classifier: Programming Language :: Python :: 3.9
Classifier: Programming Language :: Python :: 3.10
Classifier: Programming Language :: Python :: 3.11
Classifier: Programming Language :: Python :: 3.12
Requires-Dist: XlsxWriter (>=3.2.0,<4.0.0)
Requires-Dist: ipfabric[pd] (>=6.7.2,<7.0.0)
Requires-Dist: rich (>=13.7.1,<14.0.0)
Requires-Dist: tabulate (>=0.9.0,<0.10.0)
